Workbook

Sheet Инструкция
A1: Калькулятор МВ-Cu: выбор дозы и экономическая эффективность
A3: Как пользоваться
A4: 1. Лист «Исходные»: замените синие значения на жёлтом фоне данными своей фабрики и результатами испытаний.
A5: 2. Лист «Доза-отклик»: внесите результаты лабораторных опытов по каждой дозе (синие ячейки). Оптимальная доза считается автоматически.
A6: 3. Лист «Экономика»: годовой эффект при дозе из листа «Исходные». Сюда же выведены точки безубыточности.
A7: 4. Лист «Чувствительность»: чистый эффект при разных приростах производительности, ценах реагента и меди.
A8: 5. Лист «Скоринг составов»: сравнение кандидатов после этапов 0–4 методики. Флотация, сгущение и Ca-стабильность — обязательные барьеры (1 = прошёл, 0 = не прошёл).
A10: Цветовые обозначения
A11: Синий текст — вводимые значения. Жёлтый фон — ключевые допущения, заменить своими данными.
A12: Чёрный текст — формулы. Зелёный текст — ссылки на другой лист.
A14: ВАЖНО: все числа во вводимых ячейках — ПРИМЕР (иллюстративные допущения), а не данные испытаний или котировки.
A15: Цены меди, реагента, флокулянта и электроэнергии нужно заменить актуальными котировками и тарифами. Эффекты (прирост производительности, извлечения) — результатами опытов.
A16: Методика испытаний: docs/research/copper-mill-viscosity-modifier-lab-methodology.md

Sheet Исходные
A1: Исходные данные (ПРИМЕР — заменить данными фабрики и результатами испытаний)
A3: Параметр | B3: Значение | C3: Ед. изм. | D3: Источник / комментарий
A4: Базовая производительность секции (мельницы) | B4: 1000 | C4: т/ч | D4: Допущение для примера; взять из отчётов фабрики
A5: Часы работы в год | B5: 8000 | C5: ч/год | D5: Допущение: около 91 % готовности
A6: Содержание Cu в руде | B6: 0.005 | C6: доля | D6: Допущение: 0,50 % Cu
A7: Извлечение Cu базовое | B7: 0.88 | C7: доля | D7: Допущение
A8: Оплачиваемая доля Cu в концентрате | B8: 0.965 | C8: доля | D8: Допущение; по контракту на концентрат
A9: Цена Cu | B9: 9500 | C9: $/т | D9: Допущение; заменить текущей котировкой LME
A10: TC/RC, фрахт, штрафы | B10: 0.15 | C10: доля выручки | D10: Допущение; по контракту на концентрат
A11: Переменные затраты на дополнительную тонну руды (добыча + переработка, без МВ-Cu) | B11: 12 | C11: $/т | D11: Допущение; из бюджета фабрики. Если руда на складе уже добыта — только переработка
A12: Мельница — узкое место? (1 = да, 0 = нет) | B12: 1 | C12: флаг | D12: 1 — эффект считаем как прирост производительности; 0 — как экономию электроэнергии
A13: Удельный расход энергии на измельчение | B13: 14 | C13: кВт·ч/т | D13: Допущение; по учёту фабрики (МСИ + шаровая)
A14: Цена электроэнергии | B14: 0.06 | C14: $/кВт·ч | D14: Допущение; тариф предприятия
A15: Доза МВ-Cu по активному веществу | B15: 50 | C15: г/т | D15: Стартовая доза из отчёта; уточнить по листу «Доза-отклик»
... A24: Капзатраты: узел хранения и дозирования | B24: 150000 | C24: $ | D24: Допущение: ёмкость, насосы-дозаторы, КИП, монтаж

Sheet Экономика
A1: Годовой экономический эффект МВ-Cu
A3: Показатель | B3: Значение | C3: Ед. изм. | D3: Формула / комментарий
A4: Базовая переработка руды | B4: =Исходные!$B$4*Исходные!$B$5 -> 8000000 | C4: т/год | D4: Q0 × H
A5: Выручка NSR на 1 т руды | B5: =Исходные!$B$6*Исходные!$B$7*Исходные!$B$8*Исходные!$B$9*(1-Исходные!$B$10) -> 34.28645 | C5: $/т | D5: Cu × R × payable × цена × (1 − TC/RC)
A6: Маржа на дополнительную тонну руды | B6: =B5-Исходные!$B$11 -> 22.28645 | C6: $/т | D6: NSR − переменные затраты
A7: Прирост производительности (применённый) | B7: =IF(Исходные!$B$12=1,Исходные!$B$18*Исходные!$B$23,0) -> 0.03 | C7: доля | D7: Лабораторный × коэффициент переноса; только если мельница — узкое место
A8: Снижение удельной энергии (применённое) | B8: =IF(Исходные!$B$12=1,0,Исходные!$B$19*Исходные!$B$23) -> 0 | C8: доля | D8: Только если мельница не узкое место
A9: Прирост извлечения (применённый) | B9: =Исходные!$B$20*Исходные!$B$23 -> 0.001 | C9: абс. доля | D9: Лабораторный × коэффициент переноса
A10: Переработка с МВ-Cu | B10: =B4*(1+B7) -> 8240000 | C10: т/год
A11: Расход товарного продукта | B11: =Исходные!$B$15/Исходные!$B$16 -> 131.57895 | C11: г/т руды | D11: Доза по активу / доля актива
A12: Стоимость МВ-Cu на 1 т руды | B12: =B11/1000*Исходные!$B$17 -> 0.32894737 | C12: $/т
A13: Изменение затрат на флокулянт на 1 т руды | B13: =Исходные!$B$21/1000*Исходные!$B$22 -> 0 | C13: $/т
A14: Потребность в товарном продукте | B14: =B10*B11/1000000 -> 1084.2105 | C14: т/год | D14: Для заказа и складских запасов
A16: Выгода: прирост производительности | B16: =B4*B7*B6 -> 5348748 | C16: $/год | D16: ΔQ × маржа
A17: Выгода: экономия электроэнергии | B17: =B4*Исходные!$B$13*B8*Исходные!$B$14 -> 0 | C17: $/год
A18: Выгода: прирост извлечения | B18: =B10*Исходные!$B$6*B9*Исходные!$B$8*Исходные!$B$9*(1-Исходные!$B$10) -> 321045.85 | C18: $/год
A19: Затраты: МВ-Cu | B19: =-B10*B12 -> -2710526.3 | C19: $/год
A20: Затраты: изменение расхода флокулянта | B20: =-B10*B13 -> 0 | C20: $/год
A21: ЧИСТЫЙ ГОДОВОЙ ЭФФЕКТ | B21: =SUM(B16:B20) -> 2959267.5 | C21: $/год
A22: Чистый эффект на 1 т переработанной руды | B22: =IF(B10>0,B21/B10,0) -> 0.35913441 | C22: $/т
A23: Отдача на 1 $ затрат на реагент | B23: =IF(B19<0,(B16+B17+B18)/-B19,0) -> 2.0917686 | C23: x | D23: Выгоды / затраты на МВ-Cu
A24: Срок окупаемости капзатрат | B24: =IF(B21>0,Исходные!$B$24/(B21/12),"не окупается") -> 0.60825862 | C24: мес.
A26: Точки безубыточности
A27: Минимальный прирост производительности (без эффекта извлечения) | B27: =IF(B6>(B12+B13),(B12+B13)/(B6-B12-B13),"недостижим") -> 0.014981092 | C27: доля | D27: δ·m = (1+δ)·c → δ = c/(m − c)
A28: Минимальный прирост извлечения (при той же производительности) | B28: =(B12+B13)/(Исходные!$B$6*Исходные!$B$8*Исходные!$B$9*(1-Исходные!$B$10)) -> 0.0084428013 | C28: абс. доля
A29: Минимальная экономия энергии (при той же производительности) | B29: =(B12+B13)/(Исходные!$B$13*Исходные!$B$14) -> 0.39160401 | C29: доля | D29: Больше 100 % — экономия энергии сама по себе реагент не окупает
A30: Максимальная цена продукта, при которой эффект ≥ 0 | B30: =IF(B11>0,(B16+B17+B18+B20)/B10/(B11/1000),0) -> 5.2294215 | C30: $/кг

Sheet Доза-отклик
A1: Подбор дозы по лабораторным данным (ПРИМЕР — заменить результатами этапа 5 методики)
A2: Вводить: доза, t80, ΔCw, прирост извлечения и отметки барьеров. Остальное считается. Первая строка — холостой опыт (доза 0).
A4: Доза по активу, г/т | B4: t80 до целевой P80, мин (Cw рабочая +3 п.п.) | C4: ΔCw при равном τy, п.п. | D4: Прирост извлечения (лаб.), абс. | E4: Флотация: барьер пройден (1/0) | F4: Сгущение: барьер пройден (1/0) | G4: Прирост производительности (лаб.) | H4: Прирост производительности (примен.) | I4: Переработка, т/год | J4: Выгода: производительность, $/год | K4: Выгода: извлечение, $/год | L4: Затраты: МВ-Cu, $/год | M4: Чистый эффект, $/год | N4: Чистый эффект (только допустимые дозы), $/год
A5: 0 | B5: 12 | C5: 0 | D5: 0 | E5: 1 | F5: 1 | G5: =IF(B5>0,$B$5/B5-1,0) -> 0 | H5: =IF(Исходные!$B$12=1,G5*Исходные!$B$23,0) -> 0 | I5: =Исходные!$B$4*Исходные!$B$5*(1+H5) -> 8000000 | J5: =Исходные!$B$4*Исходные!$B$5*H5*(Экономика!$B$6) -> 0 | K5: =I5*Исходные!$B$6*D5*Исходные!$B$23*Исходные!$B$8*Исходные!$B$9*(1-Исходные!$B$10) -> 0 | L5: =-I5*A5/Исходные!$B$16/1000*Исходные!$B$17 -> 0 | M5: =J5+K5+L5 -> 0 | N5: =IF(AND(E5=1,F5=1),M5,"") -> 0
A6: 15 | B6: 11.71 | C6: 0.8 | D6: 0 | E6: 1 | F6: 1 | G6: =IF(B6>0,$B$5/B6-1,0) -> 0.024765158 | H6: =IF(Исходные!$B$12=1,G6*Исходные!$B$23,0) -> 0.012382579 | I6: =Исходные!$B$4*Исходные!$B$5*(1+H6) -> 8099060.6 | J6: =Исходные!$B$4*Исходные!$B$5*H6*(Экономика!$B$6) -> 2207709.8 | K6: =I6*Исходные!$B$6*D6*Исходные!$B$23*Исходные!$B$8*Исходные!$B$9*(1-Исходные!$B$10) -> 0 | L6: =-I6*A6/Исходные!$B$16/1000*Исходные!$B$17 -> -799249.4 | M6: =J6+K6+L6 -> 1408460.4 | N6: =IF(AND(E6=1,F6=1),M6,"") -> 1408460.4
A7: 30 | B7: 11.48 | C7: 1.6 | D7: 0.001 | E7: 1 | F7: 1 | G7: =IF(B7>0,$B$5/B7-1,0) -> 0.045296167 | H7: =IF(Исходные!$B$12=1,G7*Исходные!$B$23,0) -> 0.022648084 | I7: =Исходные!$B$4*Исходные!$B$5*(1+H7) -> 8181184.7 | J7: =Исходные!$B$4*Исходные!$B$5*H7*(Экономика!$B$6) -> 4037963.1 | K7: =I7*Исходные!$B$6*D7*Исходные!$B$23*Исходные!$B$8*Исходные!$B$9*(1-Исходные!$B$10) -> 159377.15 | L7: =-I7*A7/Исходные!$B$16/1000*Исходные!$B$17 -> -1614707.5 | M7: =J7+K7+L7 -> 2582632.7 | N7: =IF(AND(E7=1,F7=1),M7,"") -> 2582632.7
A8: 50 | B8: 11.32 | C8: 2.4 | D8: 0.002 | E8: 1 | F8: 1 | G8: =IF(B8>0,$B$5/B8-1,0) -> 0.060070671 | H8: =IF(Исходные!$B$12=1,G8*Исходные!$B$23,0) -> 0.030035336 | I8: =Исходные!$B$4*Исходные!$B$5*(1+H8) -> 8240282.7 | J8: =Исходные!$B$4*Исходные!$B$5*H8*(Экономика!$B$6) -> 5355048.1 | K8: =I8*Исходные!$B$6*D8*Исходные!$B$23*Исходные!$B$8*Исходные!$B$9*(1-Исходные!$B$10) -> 321056.86 | L8: =-I8*A8/Исходные!$B$16/1000*Исходные!$B$17 -> -2710619.3 | M8: =J8+K8+L8 -> 2965485.6 | N8: =IF(AND(E8=1,F8=1),M8,"") -> 2965485.6
A9: 75 | B9: 11.24 | C9: 2.8 | D9: 0.002 | E9: 1 | F9: 1 | G9: =IF(B9>0,$B$5/B9-1,0) -> 0.067615658 | H9: =IF(Исходные!$B$12=1,G9*Исходные!$B$23,0) -> 0.033807829 | I9: =Исходные!$B$4*Исходные!$B$5*(1+H9) -> 8270462.6 | J9: =Исходные!$B$4*Исходные!$B$5*H9*(Экономика!$B$6) -> 6027652 | K9: =I9*Исходные!$B$6*D9*Исходные!$B$23*Исходные!$B$8*Исходные!$B$9*(1-Исходные!$B$10) -> 322232.73 | L9: =-I9*A9/Исходные!$B$16/1000*Исходные!$B$17 -> -4080820.4 | M9: =J9+K9+L9 -> 2269064.3 | N9: =IF(AND(E9=1,F9=1),M9,"") -> 2269064.3
A10: 100 | B10: 11.19 | C10: 3 | D10: 0.002 | E10: 1 | F10: 1 | G10: =IF(B10>0,$B$5/B10-1,0) -> 0.072386059 | H10: =IF(Исходные!$B$12=1,G10*Исходные!$B$23,0) -> 0.036193029 | I10: =Исходные!$B$4*Исходные!$B$5*(1+H10) -> 8289544.2 | J10: =Исходные!$B$4*Исходные!$B$5*H10*(Экономика!$B$6) -> 6452913.1 | K10: =I10*Исходные!$B$6*D10*Исходные!$B$23*Исходные!$B$8*Исходные!$B$9*(1-Исходные!$B$10) -> 322976.19 | L10: =-I10*A10/Исходные!$B$16/1000*Исходные!$B$17 -> -5453647.5 | M10: =J10+K10+L10 -> 1322241.8 | N10: =IF(AND(E10=1,F10=1),M10,"") -> 1322241.8
A11: 150 | B11: 11.17 | C11: 3.1 | D11: 0.001 | E11: 0 | F11: 1 | G11: =IF(B11>0,$B$5/B11-1,0) -> 0.074306177 | H11: =IF(Исходные!$B$12=1,G11*Исходные!$B$23,0) -> 0.037153089 | I11: =Исходные!$B$4*Исходные!$B$5*(1+H11) -> 8297224.7 | J11: =Исходные!$B$4*Исходные!$B$5*H11*(Экономика!$B$6) -> 6624083.6 | K11: =I11*Исходные!$B$6*D11*Исходные!$B$23*Исходные!$B$8*Исходные!$B$9*(1-Исходные!$B$10) -> 161637.72 | L11: =-I11*A11/Исходные!$B$16/1000*Исходные!$B$17 -> -8188050.7 | M11: =J11+K11+L11 -> -1402329.4 | N11: =IF(AND(E11=1,F11=1),M11,"")
A13: Экономически оптимальная доза (среди допустимых), г/т | D13: =INDEX(A5:A11,MATCH(MAX(N5:N11),N5:N11,0)) -> 50
A14: Чистый эффект при оптимальной дозе, $/год | D14: =MAX(N5:N11) -> 2965485.6
A15: Максимальная безопасная доза (наибольшая доза, прошедшая оба барьера), г/т | D15: =SUMPRODUCT(MAX((E5:E11=1)*(F5:F11=1)*A5:A11)) -> 100
A16: Запас по дозе: безопасная / оптимальная (требование методики ≥ 3; если ниже — выбрать меньшую дозу) | D16: =IF(D13>0,D15/D13,0) -> 2
A18: Примечания: прирост производительности (лаб.) = t80 холостого / t80 с реагентом − 1 при одинаковой плотности пульпы. «Барьер пройден» = разница с холостым опытом в пределах критериев раздела 9 методики. Колонка N пустая для доз, не прошедших барьеры.

Sheet Чувствительность
A1: Чувствительность чистого годового эффекта, $/год
A2: Прочие параметры берутся из листа «Исходные» (доза, извлечение, флокулянт, коэффициент переноса для прироста извлечения). Прирост производительности в таблицах — уже применённый (промышленный).
A4: Таблица 1. Прирост производительности (строки) × цена продукта МВ-Cu, $/кг (столбцы)
A5: ΔQ \ цена | B5: 1.5 | C5: 2 | D5: 2.5 | E5: 3 | F5: 4
A6: 0 | B6: =Исходные!$B$4*Исходные!$B$5*$A6*(Исходные!$B$6*Исходные!$B$7*Исходные!$B$8*Исходные!$B$9*(1-Исходные!$B$10)-Исходные!$B$11)+Исходные!$B$4*Исходные!$B$5*(1+$A6)*Исходные!$B$6*Исходные!$B$20*Исходные!$B$23*Исходные!$B$8*Исходные!$B$9*(1-Исходные!$B$10)-Исходные!$B$4*Исходные!$B$5*(1+$A6)*(Исходные!$B$15/Исходные!$B$16/1000*B$5+Исходные!$B$21/1000*Исходные!$B$22) -> -1267252.4 | C6: =Исходные!$B$4*Исходные!$B$5*$A6*(Исходные!$B$6*Исходные!$B$7*Исходные!$B$8*Исходные!$B$9*(1-Исходные!$B$10)-Исходные!$B$11)+Исходные!$B$4*Исходные!$B$5*(1+$A6)*Исходные!$B$6*Исходные!$B$20*Исходные!$B$23*Исходные!$B$8*Исходные!$B$9*(1-Исходные!$B$10)-Исходные!$B$4*Исходные!$B$5*(1+$A6)*(Исходные!$B$15/Исходные!$B$16/1000*C$5+Исходные!$B$21/1000*Исходные!$B$22) -> -1793568.2 | D6: =Исходные!$B$4*Исходные!$B$5*$A6*(Исходные!$B$6*Исходные!$B$7*Исходные!$B$8*Исходные!$B$9*(1-Исходные!$B$10)-Исходные!$B$11)+Исходные!$B$4*Исходные!$B$5*(1+$A6)*Исходные!$B$6*Исходные!$B$20*Исходные!$B$23*Исходные!$B$8*Исходные!$B$9*(1-Исходные!$B$10)-Исходные!$B$4*Исходные!$B$5*(1+$A6)*(Исходные!$B$15/Исходные!$B$16/1000*D$5+Исходные!$B$21/1000*Исходные!$B$22) -> -2319883.9 | E6: =Исходные!$B$4*Исходные!$B$5*$A6*(Исходные!$B$6*Исходные!$B$7*Исходные!$B$8*Исходные!$B$9*(1-Исходные!$B$10)-Исходные!$B$11)+Исходные!$B$4*Исходные!$B$5*(1+$A6)*Исходные!$B$6*Исходные!$B$20*Исходные!$B$23*Исходные!$B$8*Исходные!$B$9*(1-Исходные!$B$10)-Исходные!$B$4*Исходные!$B$5*(1+$A6)*(Исходные!$B$15/Исходные!$B$16/1000*E$5+Исходные!$B$21/1000*Исходные!$B$22) -> -2846199.7 | F6: =Исходные!$B$4*Исходные!$B$5*$A6*(Исходные!$B$6*Исходные!$B$7*Исходные!$B$8*Исходные!$B$9*(1-Исходные!$B$10)-Исходные!$B$11)+Исходные!$B$4*Исходные!$B$5*(1+$A6)*Исходные!$B$6*Исходные!$B$20*Исходные!$B$23*Исходные!$B$8*Исходные!$B$9*(1-Исходные!$B$10)-Исходные!$B$4*Исходные!$B$5*(1+$A6)*(Исходные!$B$15/Исходные!$B$16/1000*F$5+Исходные!$B$21/1000*Исходные!$B$22) -> -3898831.3
A7: 0.01 | B7: =Исходные!$B$4*Исходные!$B$5*$A7*(Исходные!$B$6*Исходные!$B$7*Исходные!$B$8*Исходные!$B$9*(1-Исходные!$B$10)-Исходные!$B$11)+Исходные!$B$4*Исходные!$B$5*(1+$A7)*Исходные!$B$6*Исходные!$B$20*Исходные!$B$23*Исходные!$B$8*Исходные!$B$9*(1-Исходные!$B$10)-Исходные!$B$4*Исходные!$B$5*(1+$A7)*(Исходные!$B$15/Исходные!$B$16/1000*B$5+Исходные!$B$21/1000*Исходные!$B$22) -> 502991.11 | C7: =Исходные!$B$4*Исходные!$B$5*$A7*(Исходные!$B$6*Исходные!$B$7*Исходные!$B$8*Исходные!$B$9*(1-Исходные!$B$10)-Исходные!$B$11)+Исходные!$B$4*Исходные!$B$5*(1+$A7)*Исходные!$B$6*Исходные!$B$20*Исходные!$B$23*Исходные!$B$8*Исходные!$B$9*(1-Исходные!$B$10)-Исходные!$B$4*Исходные!$B$5*(1+$A7)*(Исходные!$B$15/Исходные!$B$16/1000*C$5+Исходные!$B$21/1000*Исходные!$B$22) -> -28587.839 | D7: =Исходные!$B$4*Исходные!$B$5*$A7*(Исходные!$B$6*Исходные!$B$7*Исходные!$B$8*Исходные!$B$9*(1-Исходные!$B$10)-Исходные!$B$11)+Исходные!$B$4*Исходные!$B$5*(1+$A7)*Исходные!$B$6*Исходные!$B$20*Исходные!$B$23*Исходные!$B$8*Исходные!$B$9*(1-Исходные!$B$10)-Исходные!$B$4*Исходные!$B$5*(1+$A7)*(Исходные!$B$15/Исходные!$B$16/1000*D$5+Исходные!$B$21/1000*Исходные!$B$22) -> -560166.79 | E7: =Исходные!$B$4*Исходные!$B$5*$A7*(Исходные!$B$6*Исходные!$B$7*Исходные!$B$8*Исходные!$B$9*(1-Исходные!$B$10)-Исходные!$B$11)+Исходные!$B$4*Исходные!$B$5*(1+$A7)*Исходные!$B$6*Исходные!$B$20*Исходные!$B$23*Исходные!$B$8*Исходные!$B$9*(1-Исходные!$B$10)-Исходные!$B$4*Исходные!$B$5*(1+$A7)*(Исходные!$B$15/Исходные!$B$16/1000*E$5+Исходные!$B$21/1000*Исходные!$B$22) -> -1091745.7 | F7: =Исходные!$B$4*Исходные!$B$5*$A7*(Исходные!$B$6*Исходные!$B$7*Исходные!$B$8*Исходные!$B$9*(1-Исходные!$B$10)-Исходные!$B$11)+Исходные!$B$4*Исходные!$B$5*(1+$A7)*Исходные!$B$6*Исходные!$B$20*Исходные!$B$23*Исходные!$B$8*Исходные!$B$9*(1-Исходные!$B$10)-Исходные!$B$4*Исходные!$B$5*(1+$A7)*(Исходные!$B$15/Исходные!$B$16/1000*F$5+Исходные!$B$21/1000*Исходные!$B$22) -> -2154903.6
A8: 0.02 | B8: =Исходные!$B$4*Исходные!$B$5*$A8*(Исходные!$B$6*Исходные!$B$7*Исходные!$B$8*Исходные!$B$9*(1-Исходные!$B$10)-Исходные!$B$11)+Исходные!$B$4*Исходные!$B$5*(1+$A8)*Исходные!$B$6*Исходные!$B$20*Исходные!$B$23*Исходные!$B$8*Исходные!$B$9*(1-Исходные!$B$10)-Исходные!$B$4*Исходные!$B$5*(1+$A8)*(Исходные!$B$15/Исходные!$B$16/1000*B$5+Исходные!$B$21/1000*Исходные!$B$22) -> 2273234.6 | C8: =Исходные!$B$4*Исходные!$B$5*$A8*(Исходные!$B$6*Исходные!$B$7*Исходные!$B$8*Исходные!$B$9*(1-Исходные!$B$10)-Исходные!$B$11)+Исходные!$B$4*Исходные!$B$5*(1+$A8)*Исходные!$B$6*Исходные!$B$20*Исходные!$B$23*Исходные!$B$8*Исходные!$B$9*(1-Исходные!$B$10)-Исходные!$B$4*Исходные!$B$5*(1+$A8)*(Исходные!$B$15/Исходные!$B$16/1000*C$5+Исходные!$B$21/1000*Исходные!$B$22) -> 1736392.5 | D8: =Исходные!$B$4*Исходные!$B$5*$A8*(Исходные!$B$6*Исходные!$B$7*Исходные!$B$8*Исходные!$B$9*(1-Исходные!$B$10)-Исходные!$B$11)+Исходные!$B$4*Исходные!$B$5*(1+$A8)*Исходные!$B$6*Исходные!$B$20*Исходные!$B$23*Исходные!$B$8*Исходные!$B$9*(1-Исходные!$B$10)-Исходные!$B$4*Исходные!$B$5*(1+$A8)*(Исходные!$B$15/Исходные!$B$16/1000*D$5+Исходные!$B$21/1000*Исходные!$B$22) -> 1199550.4 | E8: =Исходные!$B$4*Исходные!$B$5*$A8*(Исходные!$B$6*Исходные!$B$7*Исходные!$B$8*Исходные!$B$9*(1-Исходные!$B$10)-Исходные!$B$11)+Исходные!$B$4*Исходные!$B$5*(1+$A8)*Исходные!$B$6*Исходные!$B$20*Исходные!$B$23*Исходные!$B$8*Исходные!$B$9*(1-Исходные!$B$10)-Исходные!$B$4*Исходные!$B$5*(1+$A8)*(Исходные!$B$15/Исходные!$B$16/1000*E$5+Исходные!$B$21/1000*Исходные!$B$22) -> 662708.27 | F8: =Исходные!$B$4*Исходные!$B$5*$A8*(Исходные!$B$6*Исходные!$B$7*Исходные!$B$8*Исходные!$B$9*(1-Исходные!$B$10)-Исходные!$B$11)+Исходные!$B$4*Исходные!$B$5*(1+$A8)*Исходные!$B$6*Исходные!$B$20*Исходные!$B$23*Исходные!$B$8*Исходные!$B$9*(1-Исходные!$B$10)-Исходные!$B$4*Исходные!$B$5*(1+$A8)*(Исходные!$B$15/Исходные!$B$16/1000*F$5+Исходные!$B$21/1000*Исходные!$B$22) -> -410975.94
A9: 0.03 | B9: =Исходные!$B$4*Исходные!$B$5*$A9*(Исходные!$B$6*Исходные!$B$7*Исходные!$B$8*Исходные!$B$9*(1-Исходные!$B$10)-Исходные!$B$11)+Исходные!$B$4*Исходные!$B$5*(1+$A9)*Исходные!$B$6*Исходные!$B$20*Исходные!$B$23*Исходные!$B$8*Исходные!$B$9*(1-Исходные!$B$10)-Исходные!$B$4*Исходные!$B$5*(1+$A9)*(Исходные!$B$15/Исходные!$B$16/1000*B$5+Исходные!$B$21/1000*Исходные!$B$22) -> 4043478.1 | C9: =Исходные!$B$4*Исходные!$B$5*$A9*(Исходные!$B$6*Исходные!$B$7*Исходные!$B$8*Исходные!$B$9*(1-Исходные!$B$10)-Исходные!$B$11)+Исходные!$B$4*Исходные!$B$5*(1+$A9)*Исходные!$B$6*Исходные!$B$20*Исходные!$B$23*Исходные!$B$8*Исходные!$B$9*(1-Исходные!$B$10)-Исходные!$B$4*Исходные!$B$5*(1+$A9)*(Исходные!$B$15/Исходные!$B$16/1000*C$5+Исходные!$B$21/1000*Исходные!$B$22) -> 3501372.8 | D9: =Исходные!$B$4*Исходные!$B$5*$A9*(Исходные!$B$6*Исходные!$B$7*Исходные!$B$8*Исходные!$B$9*(1-Исходные!$B$10)-Исходные!$B$11)+Исходные!$B$4*Исходные!$B$5*(1+$A9)*Исходные!$B$6*Исходные!$B$20*Исходные!$B$23*Исходные!$B$8*Исходные!$B$9*(1-Исходные!$B$10)-Исходные!$B$4*Исходные!$B$5*(1+$A9)*(Исходные!$B$15/Исходные!$B$16/1000*D$5+Исходные!$B$21/1000*Исходные!$B$22) -> 2959267.5 | E9: =Исходные!$B$4*Исходные!$B$5*$A9*(Исходные!$B$6*Исходные!$B$7*Исходные!$B$8*Исходные!$B$9*(1-Исходные!$B$10)-Исходные!$B$11)+Исходные!$B$4*Исходные!$B$5*(1+$A9)*Исходные!$B$6*Исходные!$B$20*Исходные!$B$23*Исходные!$B$8*Исходные!$B$9*(1-Исходные!$B$10)-Исходные!$B$4*Исходные!$B$5*(1+$A9)*(Исходные!$B$15/Исходные!$B$16/1000*E$5+Исходные!$B$21/1000*Исходные!$B$22) -> 2417162.3 | F9: =Исходные!$B$4*Исходные!$B$5*$A9*(Исходные!$B$6*Исходные!$B$7*Исходные!$B$8*Исходные!$B$9*(1-Исходные!$B$10)-Исходные!$B$11)+Исходные!$B$4*Исходные!$B$5*(1+$A9)*Исходные!$B$6*Исходные!$B$20*Исходные!$B$23*Исходные!$B$8*Исходные!$B$9*(1-Исходные!$B$10)-Исходные!$B$4*Исходные!$B$5*(1+$A9)*(Исходные!$B$15/Исходные!$B$16/1000*F$5+Исходные!$B$21/1000*Исходные!$B$22) -> 1332951.7
A10: 0.05 | B10: =Исходные!$B$4*Исходные!$B$5*$A10*(Исходные!$B$6*Исходные!$B$7*Исходные!$B$8*Исходные!$B$9*(1-Исходные!$B$10)-Исходные!$B$11)+Исходные!$B$4*Исходные!$B$5*(1+$A10)*Исходные!$B$6*Исходные!$B$20*Исходные!$B$23*Исходные!$B$8*Исходные!$B$9*(1-Исходные!$B$10)-Исходные!$B$4*Исходные!$B$5*(1+$A10)*(Исходные!$B$15/Исходные!$B$16/1000*B$5+Исходные!$B$21/1000*Исходные!$B$22) -> 7583965 | C10: =Исходные!$B$4*Исходные!$B$5*$A10*(Исходные!$B$6*Исходные!$B$7*Исходные!$B$8*Исходные!$B$9*(1-Исходные!$B$10)-Исходные!$B$11)+Исходные!$B$4*Исходные!$B$5*(1+$A10)*Исходные!$B$6*Исходные!$B$20*Исходные!$B$23*Исходные!$B$8*Исходные!$B$9*(1-Исходные!$B$10)-Исходные!$B$4*Исходные!$B$5*(1+$A10)*(Исходные!$B$15/Исходные!$B$16/1000*C$5+Исходные!$B$21/1000*Исходные!$B$22) -> 7031333.4 | D10: =Исходные!$B$4*Исходные!$B$5*$A10*(Исходные!$B$6*Исходные!$B$7*Исходные!$B$8*Исходные!$B$9*(1-Исходные!$B$10)-Исходные!$B$11)+Исходные!$B$4*Исходные!$B$5*(1+$A10)*Исходные!$B$6*Исходные!$B$20*Исходные!$B$23*Исходные!$B$8*Исходные!$B$9*(1-Исходные!$B$10)-Исходные!$B$4*Исходные!$B$5*(1+$A10)*(Исходные!$B$15/Исходные!$B$16/1000*D$5+Исходные!$B$21/1000*Исходные!$B$22) -> 6478701.9 | E10: =Исходные!$B$4*Исходные!$B$5*$A10*(Исходные!$B$6*Исходные!$B$7*Исходные!$B$8*Исходные!$B$9*(1-Исходные!$B$10)-Исходные!$B$11)+Исходные!$B$4*Исходные!$B$5*(1+$A10)*Исходные!$B$6*Исходные!$B$20*Исходные!$B$23*Исходные!$B$8*Исходные!$B$9*(1-Исходные!$B$10)-Исходные!$B$4*Исходные!$B$5*(1+$A10)*(Исходные!$B$15/Исходные!$B$16/1000*E$5+Исходные!$B$21/1000*Исходные!$B$22) -> 5926070.3 | F10: =Исходные!$B$4*Исходные!$B$5*$A10*(Исходные!$B$6*Исходные!$B$7*Исходные!$B$8*Исходные!$B$9*(1-Исходные!$B$10)-Исходные!$B$11)+Исходные!$B$4*Исходные!$B$5*(1+$A10)*Исходные!$B$6*Исходные!$B$20*Исходные!$B$23*Исходные!$B$8*Исходные!$B$9*(1-Исходные!$B$10)-Исходные!$B$4*Исходные!$B$5*(1+$A10)*(Исходные!$B$15/Исходные!$B$16/1000*F$5+Исходные!$B$21/1000*Исходные!$B$22) -> 4820807.1
A11: 0.07 | B11: =Исходные!$B$4*Исходные!$B$5*$A11*(Исходные!$B$6*Исходные!$B$7*Исходные!$B$8*Исходные!$B$9*(1-Исходные!$B$10)-Исходные!$B$11)+Исходные!$B$4*Исходные!$B$5*(1+$A11)*Исходные!$B$6*Исходные!$B$20*Исходные!$B$23*Исходные!$B$8*Исходные!$B$9*(1-Исходные!$B$10)-Исходные!$B$4*Исходные!$B$5*(1+$A11)*(Исходные!$B$15/Исходные!$B$16/1000*B$5+Исходные!$B$21/1000*Исходные!$B$22) -> 11124452 | C11: =Исходные!$B$4*Исходные!$B$5*$A11*(Исходные!$B$6*Исходные!$B$7*Исходные!$B$8*Исходные!$B$9*(1-Исходные!$B$10)-Исходные!$B$11)+Исходные!$B$4*Исходные!$B$5*(1+$A11)*Исходные!$B$6*Исходные!$B$20*Исходные!$B$23*Исходные!$B$8*Исходные!$B$9*(1-Исходные!$B$10)-Исходные!$B$4*Исходные!$B$5*(1+$A11)*(Исходные!$B$15/Исходные!$B$16/1000*C$5+Исходные!$B$21/1000*Исходные!$B$22) -> 10561294 | D11: =Исходные!$B$4*Исходные!$B$5*$A11*(Исходные!$B$6*Исходные!$B$7*Исходные!$B$8*Исходные!$B$9*(1-Исходные!$B$10)-Исходные!$B$11)+Исходные!$B$4*Исходные!$B$5*(1+$A11)*Исходные!$B$6*Исходные!$B$20*Исходные!$B$23*Исходные!$B$8*Исходные!$B$9*(1-Исходные!$B$10)-Исходные!$B$4*Исходные!$B$5*(1+$A11)*(Исходные!$B$15/Исходные!$B$16/1000*D$5+Исходные!$B$21/1000*Исходные!$B$22) -> 9998136.2 | E11: =Исходные!$B$4*Исходные!$B$5*$A11*(Исходные!$B$6*Исходные!$B$7*Исходные!$B$8*Исходные!$B$9*(1-Исходные!$B$10)-Исходные!$B$11)+Исходные!$B$4*Исходные!$B$5*(1+$A11)*Исходные!$B$6*Исходные!$B$20*Исходные!$B$23*Исходные!$B$8*Исходные!$B$9*(1-Исходные!$B$10)-Исходные!$B$4*Исходные!$B$5*(1+$A11)*(Исходные!$B$15/Исходные!$B$16/1000*E$5+Исходные!$B$21/1000*Исходные!$B$22) -> 9434978.3 | F11: =Исходные!$B$4*Исходные!$B$5*$A11*(Исходные!$B$6*Исходные!$B$7*Исходные!$B$8*Исходные!$B$9*(1-Исходные!$B$10)-Исходные!$B$11)+Исходные!$B$4*Исходные!$B$5*(1+$A11)*Исходные!$B$6*Исходные!$B$20*Исходные!$B$23*Исходные!$B$8*Исходные!$B$9*(1-Исходные!$B$10)-Исходные!$B$4*Исходные!$B$5*(1+$A11)*(Исходные!$B$15/Исходные!$B$16/1000*F$5+Исходные!$B$21/1000*Исходные!$B$22) -> 8308662.5
A12: 0.1 | B12: =Исходные!$B$4*Исходные!$B$5*$A12*(Исходные!$B$6*Исходные!$B$7*Исходные!$B$8*Исходные!$B$9*(1-Исходные!$B$10)-Исходные!$B$11)+Исходные!$B$4*Исходные!$B$5*(1+$A12)*Исходные!$B$6*Исходные!$B$20*Исходные!$B$23*Исходные!$B$8*Исходные!$B$9*(1-Исходные!$B$10)-Исходные!$B$4*Исходные!$B$5*(1+$A12)*(Исходные!$B$15/Исходные!$B$16/1000*B$5+Исходные!$B$21/1000*Исходные!$B$22) -> 16435182 | C12: =Исходные!$B$4*Исходные!$B$5*$A12*(Исходные!$B$6*Исходные!$B$7*Исходные!$B$8*Исходные!$B$9*(1-Исходные!$B$10)-Исходные!$B$11)+Исходные!$B$4*Исходные!$B$5*(1+$A12)*Исходные!$B$6*Исходные!$B$20*Исходные!$B$23*Исходные!$B$8*Исходные!$B$9*(1-Исходные!$B$10)-Исходные!$B$4*Исходные!$B$5*(1+$A12)*(Исходные!$B$15/Исходные!$B$16/1000*C$5+Исходные!$B$21/1000*Исходные!$B$22) -> 15856235 | D12: =Исходные!$B$4*Исходные!$B$5*$A12*(Исходные!$B$6*Исходные!$B$7*Исходные!$B$8*Исходные!$B$9*(1-Исходные!$B$10)-Исходные!$B$11)+Исходные!$B$4*Исходные!$B$5*(1+$A12)*Исходные!$B$6*Исходные!$B$20*Исходные!$B$23*Исходные!$B$8*Исходные!$B$9*(1-Исходные!$B$10)-Исходные!$B$4*Исходные!$B$5*(1+$A12)*(Исходные!$B$15/Исходные!$B$16/1000*D$5+Исходные!$B$21/1000*Исходные!$B$22) -> 15277288 | E12: =Исходные!$B$4*Исходные!$B$5*$A12*(Исходные!$B$6*Исходные!$B$7*Исходные!$B$8*Исходные!$B$9*(1-Исходные!$B$10)-Исходные!$B$11)+Исходные!$B$4*Исходные!$B$5*(1+$A12)*Исходные!$B$6*Исходные!$B$20*Исходные!$B$23*Исходные!$B$8*Исходные!$B$9*(1-Исходные!$B$10)-Исходные!$B$4*Исходные!$B$5*(1+$A12)*(Исходные!$B$15/Исходные!$B$16/1000*E$5+Исходные!$B$21/1000*Исходные!$B$22) -> 14698340 | F12: =Исходные!$B$4*Исходные!$B$5*$A12*(Исходные!$B$6*Исходные!$B$7*Исходные!$B$8*Исходные!$B$9*(1-Исходные!$B$10)-Исходные!$B$11)+Исходные!$B$4*Исходные!$B$5*(1+$A12)*Исходные!$B$6*Исходные!$B$20*Исходные!$B$23*Исходные!$B$8*Исходные!$B$9*(1-Исходные!$B$10)-Исходные!$B$4*Исходные!$B$5*(1+$A12)*(Исходные!$B$15/Исходные!$B$16/1000*F$5+Исходные!$B$21/1000*Исходные!$B$22) -> 13540446
A15: Таблица 2. Прирост производительности (строки) × цена меди, $/т (столбцы)
A16: ΔQ \ цена Cu | B16: 7000 | C16: 8000 | D16: 9500 | E16: 11000 | F16: 12500
A17: 0 | B17: =Исходные!$B$4*Исходные!$B$5*$A17*(Исходные!$B$6*Исходные!$B$7*Исходные!$B$8*B$16*(1-Исходные!$B$10)-Исходные!$B$11)+Исходные!$B$4*Исходные!$B$5*(1+$A17)*Исходные!$B$6*Исходные!$B$20*Исходные!$B$23*Исходные!$B$8*B$16*(1-Исходные!$B$10)-Исходные!$B$4*Исходные!$B$5*(1+$A17)*(Исходные!$B$15/Исходные!$B$16/1000*Исходные!$B$17+Исходные!$B$21/1000*Исходные!$B$22) -> -2401908.9 | C17: =Исходные!$B$4*Исходные!$B$5*$A17*(Исходные!$B$6*Исходные!$B$7*Исходные!$B$8*C$16*(1-Исходные!$B$10)-Исходные!$B$11)+Исходные!$B$4*Исходные!$B$5*(1+$A17)*Исходные!$B$6*Исходные!$B$20*Исходные!$B$23*Исходные!$B$8*C$16*(1-Исходные!$B$10)-Исходные!$B$4*Исходные!$B$5*(1+$A17)*(Исходные!$B$15/Исходные!$B$16/1000*Исходные!$B$17+Исходные!$B$21/1000*Исходные!$B$22) -> -2369098.9 | D17: =Исходные!$B$4*Исходные!$B$5*$A17*(Исходные!$B$6*Исходные!$B$7*Исходные!$B$8*D$16*(1-Исходные!$B$10)-Исходные!$B$11)+Исходные!$B$4*Исходные!$B$5*(1+$A17)*Исходные!$B$6*Исходные!$B$20*Исходные!$B$23*Исходные!$B$8*D$16*(1-Исходные!$B$10)-Исходные!$B$4*Исходные!$B$5*(1+$A17)*(Исходные!$B$15/Исходные!$B$16/1000*Исходные!$B$17+Исходные!$B$21/1000*Исходные!$B$22) -> -2319883.9 | E17: =Исходные!$B$4*Исходные!$B$5*$A17*(Исходные!$B$6*Исходные!$B$7*Исходные!$B$8*E$16*(1-Исходные!$B$10)-Исходные!$B$11)+Исходные!$B$4*Исходные!$B$5*(1+$A17)*Исходные!$B$6*Исходные!$B$20*Исходные!$B$23*Исходные!$B$8*E$16*(1-Исходные!$B$10)-Исходные!$B$4*Исходные!$B$5*(1+$A17)*(Исходные!$B$15/Исходные!$B$16/1000*Исходные!$B$17+Исходные!$B$21/1000*Исходные!$B$22) -> -2270668.9 | F17: =Исходные!$B$4*Исходные!$B$5*$A17*(Исходные!$B$6*Исходные!$B$7*Исходные!$B$8*F$16*(1-Исходные!$B$10)-Исходные!$B$11)+Исходные!$B$4*Исходные!$B$5*(1+$A17)*Исходные!$B$6*Исходные!$B$20*Исходные!$B$23*Исходные!$B$8*F$16*(1-Исходные!$B$10)-Исходные!$B$4*Исходные!$B$5*(1+$A17)*(Исходные!$B$15/Исходные!$B$16/1000*Исходные!$B$17+Исходные!$B$21/1000*Исходные!$B$22) -> -2221453.9
A18: 0.01 | B18: =Исходные!$B$4*Исходные!$B$5*$A18*(Исходные!$B$6*Исходные!$B$7*Исходные!$B$8*B$16*(1-Исходные!$B$10)-Исходные!$B$11)+Исходные!$B$4*Исходные!$B$5*(1+$A18)*Исходные!$B$6*Исходные!$B$20*Исходные!$B$23*Исходные!$B$8*B$16*(1-Исходные!$B$10)-Исходные!$B$4*Исходные!$B$5*(1+$A18)*(Исходные!$B$15/Исходные!$B$16/1000*Исходные!$B$17+Исходные!$B$21/1000*Исходные!$B$22) -> -1364832 | C18: =Исходные!$B$4*Исходные!$B$5*$A18*(Исходные!$B$6*Исходные!$B$7*Исходные!$B$8*C$16*(1-Исходные!$B$10)-Исходные!$B$11)+Исходные!$B$4*Исходные!$B$5*(1+$A18)*Исходные!$B$6*Исходные!$B$20*Исходные!$B$23*Исходные!$B$8*C$16*(1-Исходные!$B$10)-Исходные!$B$4*Исходные!$B$5*(1+$A18)*(Исходные!$B$15/Исходные!$B$16/1000*Исходные!$B$17+Исходные!$B$21/1000*Исходные!$B$22) -> -1042965.9 | D18: =Исходные!$B$4*Исходные!$B$5*$A18*(Исходные!$B$6*Исходные!$B$7*Исходные!$B$8*D$16*(1-Исходные!$B$10)-Исходные!$B$11)+Исходные!$B$4*Исходные!$B$5*(1+$A18)*Исходные!$B$6*Исходные!$B$20*Исходные!$B$23*Исходные!$B$8*D$16*(1-Исходные!$B$10)-Исходные!$B$4*Исходные!$B$5*(1+$A18)*(Исходные!$B$15/Исходные!$B$16/1000*Исходные!$B$17+Исходные!$B$21/1000*Исходные!$B$22) -> -560166.79 | E18: =Исходные!$B$4*Исходные!$B$5*$A18*(Исходные!$B$6*Исходные!$B$7*Исходные!$B$8*E$16*(1-Исходные!$B$10)-Исходные!$B$11)+Исходные!$B$4*Исходные!$B$5*(1+$A18)*Исходные!$B$6*Исходные!$B$20*Исходные!$B$23*Исходные!$B$8*E$16*(1-Исходные!$B$10)-Исходные!$B$4*Исходные!$B$5*(1+$A18)*(Исходные!$B$15/Исходные!$B$16/1000*Исходные!$B$17+Исходные!$B$21/1000*Исходные!$B$22) -> -77367.637 | F18: =Исходные!$B$4*Исходные!$B$5*$A18*(Исходные!$B$6*Исходные!$B$7*Исходные!$B$8*F$16*(1-Исходные!$B$10)-Исходные!$B$11)+Исходные!$B$4*Исходные!$B$5*(1+$A18)*Исходные!$B$6*Исходные!$B$20*Исходные!$B$23*Исходные!$B$8*F$16*(1-Исходные!$B$10)-Исходные!$B$4*Исходные!$B$5*(1+$A18)*(Исходные!$B$15/Исходные!$B$16/1000*Исходные!$B$17+Исходные!$B$21/1000*Исходные!$B$22) -> 405431.51
A19: 0.02 | B19: =Исходные!$B$4*Исходные!$B$5*$A19*(Исходные!$B$6*Исходные!$B$7*Исходные!$B$8*B$16*(1-Исходные!$B$10)-Исходные!$B$11)+Исходные!$B$4*Исходные!$B$5*(1+$A19)*Исходные!$B$6*Исходные!$B$20*Исходные!$B$23*Исходные!$B$8*B$16*(1-Исходные!$B$10)-Исходные!$B$4*Исходные!$B$5*(1+$A19)*(Исходные!$B$15/Исходные!$B$16/1000*Исходные!$B$17+Исходные!$B$21/1000*Исходные!$B$22) -> -327755.13 | C19: =Исходные!$B$4*Исходные!$B$5*$A19*(Исходные!$B$6*Исходные!$B$7*Исходные!$B$8*C$16*(1-Исходные!$B$10)-Исходные!$B$11)+Исходные!$B$4*Исходные!$B$5*(1+$A19)*Исходные!$B$6*Исходные!$B$20*Исходные!$B$23*Исходные!$B$8*C$16*(1-Исходные!$B$10)-Исходные!$B$4*Исходные!$B$5*(1+$A19)*(Исходные!$B$15/Исходные!$B$16/1000*Исходные!$B$17+Исходные!$B$21/1000*Исходные!$B$22) -> 283167.07 | D19: =Исходные!$B$4*Исходные!$B$5*$A19*(Исходные!$B$6*Исходные!$B$7*Исходные!$B$8*D$16*(1-Исходные!$B$10)-Исходные!$B$11)+Исходные!$B$4*Исходные!$B$5*(1+$A19)*Исходные!$B$6*Исходные!$B$20*Исходные!$B$23*Исходные!$B$8*D$16*(1-Исходные!$B$10)-Исходные!$B$4*Исходные!$B$5*(1+$A19)*(Исходные!$B$15/Исходные!$B$16/1000*Исходные!$B$17+Исходные!$B$21/1000*Исходные!$B$22) -> 1199550.4 | E19: =Исходные!$B$4*Исходные!$B$5*$A19*(Исходные!$B$6*Исходные!$B$7*Исходные!$B$8*E$16*(1-Исходные!$B$10)-Исходные!$B$11)+Исходные!$B$4*Исходные!$B$5*(1+$A19)*Исходные!$B$6*Исходные!$B$20*Исходные!$B$23*Исходные!$B$8*E$16*(1-Исходные!$B$10)-Исходные!$B$4*Исходные!$B$5*(1+$A19)*(Исходные!$B$15/Исходные!$B$16/1000*Исходные!$B$17+Исходные!$B$21/1000*Исходные!$B$22) -> 2115933.7 | F19: =Исходные!$B$4*Исходные!$B$5*$A19*(Исходные!$B$6*Исходные!$B$7*Исходные!$B$8*F$16*(1-Исходные!$B$10)-Исходные!$B$11)+Исходные!$B$4*Исходные!$B$5*(1+$A19)*Исходные!$B$6*Исходные!$B$20*Исходные!$B$23*Исходные!$B$8*F$16*(1-Исходные!$B$10)-Исходные!$B$4*Исходные!$B$5*(1+$A19)*(Исходные!$B$15/Исходные!$B$16/1000*Исходные!$B$17+Исходные!$B$21/1000*Исходные!$B$22) -> 3032317
A20: 0.03 | B20: =Исходные!$B$4*Исходные!$B$5*$A20*(Исходные!$B$6*Исходные!$B$7*Исходные!$B$8*B$16*(1-Исходные!$B$10)-Исходные!$B$11)+Исходные!$B$4*Исходные!$B$5*(1+$A20)*Исходные!$B$6*Исходные!$B$20*Исходные!$B$23*Исходные!$B$8*B$16*(1-Исходные!$B$10)-Исходные!$B$4*Исходные!$B$5*(1+$A20)*(Исходные!$B$15/Исходные!$B$16/1000*Исходные!$B$17+Исходные!$B$21/1000*Исходные!$B$22) -> 709321.78 | C20: =Исходные!$B$4*Исходные!$B$5*$A20*(Исходные!$B$6*Исходные!$B$7*Исходные!$B$8*C$16*(1-Исходные!$B$10)-Исходные!$B$11)+Исходные!$B$4*Исходные!$B$5*(1+$A20)*Исходные!$B$6*Исходные!$B$20*Исходные!$B$23*Исходные!$B$8*C$16*(1-Исходные!$B$10)-Исходные!$B$4*Исходные!$B$5*(1+$A20)*(Исходные!$B$15/Исходные!$B$16/1000*Исходные!$B$17+Исходные!$B$21/1000*Исходные!$B$22) -> 1609300.1 | D20: =Исходные!$B$4*Исходные!$B$5*$A20*(Исходные!$B$6*Исходные!$B$7*Исходные!$B$8*D$16*(1-Исходные!$B$10)-Исходные!$B$11)+Исходные!$B$4*Исходные!$B$5*(1+$A20)*Исходные!$B$6*Исходные!$B$20*Исходные!$B$23*Исходные!$B$8*D$16*(1-Исходные!$B$10)-Исходные!$B$4*Исходные!$B$5*(1+$A20)*(Исходные!$B$15/Исходные!$B$16/1000*Исходные!$B$17+Исходные!$B$21/1000*Исходные!$B$22) -> 2959267.5 | E20: =Исходные!$B$4*Исходные!$B$5*$A20*(Исходные!$B$6*Исходные!$B$7*Исходные!$B$8*E$16*(1-Исходные!$B$10)-Исходные!$B$11)+Исходные!$B$4*Исходные!$B$5*(1+$A20)*Исходные!$B$6*Исходные!$B$20*Исходные!$B$23*Исходные!$B$8*E$16*(1-Исходные!$B$10)-Исходные!$B$4*Исходные!$B$5*(1+$A20)*(Исходные!$B$15/Исходные!$B$16/1000*Исходные!$B$17+Исходные!$B$21/1000*Исходные!$B$22) -> 4309235 | F20: =Исходные!$B$4*Исходные!$B$5*$A20*(Исходные!$B$6*Исходные!$B$7*Исходные!$B$8*F$16*(1-Исходные!$B$10)-Исходные!$B$11)+Исходные!$B$4*Исходные!$B$5*(1+$A20)*Исходные!$B$6*Исходные!$B$20*Исходные!$B$23*Исходные!$B$8*F$16*(1-Исходные!$B$10)-Исходные!$B$4*Исходные!$B$5*(1+$A20)*(Исходные!$B$15/Исходные!$B$16/1000*Исходные!$B$17+Исходные!$B$21/1000*Исходные!$B$22) -> 5659202.4
A21: 0.05 | B21: =Исходные!$B$4*Исходные!$B$5*$A21*(Исходные!$B$6*Исходные!$B$7*Исходные!$B$8*B$16*(1-Исходные!$B$10)-Исходные!$B$11)+Исходные!$B$4*Исходные!$B$5*(1+$A21)*Исходные!$B$6*Исходные!$B$20*Исходные!$B$23*Исходные!$B$8*B$16*(1-Исходные!$B$10)-Исходные!$B$4*Исходные!$B$5*(1+$A21)*(Исходные!$B$15/Исходные!$B$16/1000*Исходные!$B$17+Исходные!$B$21/1000*Исходные!$B$22) -> 2783475.6 | C21: =Исходные!$B$4*Исходные!$B$5*$A21*(Исходные!$B$6*Исходные!$B$7*Исходные!$B$8*C$16*(1-Исходные!$B$10)-Исходные!$B$11)+Исходные!$B$4*Исходные!$B$5*(1+$A21)*Исходные!$B$6*Исходные!$B$20*Исходные!$B$23*Исходные!$B$8*C$16*(1-Исходные!$B$10)-Исходные!$B$4*Исходные!$B$5*(1+$A21)*(Исходные!$B$15/Исходные!$B$16/1000*Исходные!$B$17+Исходные!$B$21/1000*Исходные!$B$22) -> 4261566.1 | D21: =Исходные!$B$4*Исходные!$B$5*$A21*(Исходные!$B$6*Исходные!$B$7*Исходные!$B$8*D$16*(1-Исходные!$B$10)-Исходные!$B$11)+Исходные!$B$4*Исходные!$B$5*(1+$A21)*Исходные!$B$6*Исходные!$B$20*Исходные!$B$23*Исходные!$B$8*D$16*(1-Исходные!$B$10)-Исходные!$B$4*Исходные!$B$5*(1+$A21)*(Исходные!$B$15/Исходные!$B$16/1000*Исходные!$B$17+Исходные!$B$21/1000*Исходные!$B$22) -> 6478701.9 | E21: =Исходные!$B$4*Исходные!$B$5*$A21*(Исходные!$B$6*Исходные!$B$7*Исходные!$B$8*E$16*(1-Исходные!$B$10)-Исходные!$B$11)+Исходные!$B$4*Исходные!$B$5*(1+$A21)*Исходные!$B$6*Исходные!$B$20*Исходные!$B$23*Исходные!$B$8*E$16*(1-Исходные!$B$10)-Исходные!$B$4*Исходные!$B$5*(1+$A21)*(Исходные!$B$15/Исходные!$B$16/1000*Исходные!$B$17+Исходные!$B$21/1000*Исходные!$B$22) -> 8695837.6 | F21: =Исходные!$B$4*Исходные!$B$5*$A21*(Исходные!$B$6*Исходные!$B$7*Исходные!$B$8*F$16*(1-Исходные!$B$10)-Исходные!$B$11)+Исходные!$B$4*Исходные!$B$5*(1+$A21)*Исходные!$B$6*Исходные!$B$20*Исходные!$B$23*Исходные!$B$8*F$16*(1-Исходные!$B$10)-Исходные!$B$4*Исходные!$B$5*(1+$A21)*(Исходные!$B$15/Исходные!$B$16/1000*Исходные!$B$17+Исходные!$B$21/1000*Исходные!$B$22) -> 10912973
A22: 0.07 | B22: =Исходные!$B$4*Исходные!$B$5*$A22*(Исходные!$B$6*Исходные!$B$7*Исходные!$B$8*B$16*(1-Исходные!$B$10)-Исходные!$B$11)+Исходные!$B$4*Исходные!$B$5*(1+$A22)*Исходные!$B$6*Исходные!$B$20*Исходные!$B$23*Исходные!$B$8*B$16*(1-Исходные!$B$10)-Исходные!$B$4*Исходные!$B$5*(1+$A22)*(Исходные!$B$15/Исходные!$B$16/1000*Исходные!$B$17+Исходные!$B$21/1000*Исходные!$B$22) -> 4857629.4 | C22: =Исходные!$B$4*Исходные!$B$5*$A22*(Исходные!$B$6*Исходные!$B$7*Исходные!$B$8*C$16*(1-Исходные!$B$10)-Исходные!$B$11)+Исходные!$B$4*Исходные!$B$5*(1+$A22)*Исходные!$B$6*Исходные!$B$20*Исходные!$B$23*Исходные!$B$8*C$16*(1-Исходные!$B$10)-Исходные!$B$4*Исходные!$B$5*(1+$A22)*(Исходные!$B$15/Исходные!$B$16/1000*Исходные!$B$17+Исходные!$B$21/1000*Исходные!$B$22) -> 6913832.1 | D22: =Исходные!$B$4*Исходные!$B$5*$A22*(Исходные!$B$6*Исходные!$B$7*Исходные!$B$8*D$16*(1-Исходные!$B$10)-Исходные!$B$11)+Исходные!$B$4*Исходные!$B$5*(1+$A22)*Исходные!$B$6*Исходные!$B$20*Исходные!$B$23*Исходные!$B$8*D$16*(1-Исходные!$B$10)-Исходные!$B$4*Исходные!$B$5*(1+$A22)*(Исходные!$B$15/Исходные!$B$16/1000*Исходные!$B$17+Исходные!$B$21/1000*Исходные!$B$22) -> 9998136.2 | E22: =Исходные!$B$4*Исходные!$B$5*$A22*(Исходные!$B$6*Исходные!$B$7*Исходные!$B$8*E$16*(1-Исходные!$B$10)-Исходные!$B$11)+Исходные!$B$4*Исходные!$B$5*(1+$A22)*Исходные!$B$6*Исходные!$B$20*Исходные!$B$23*Исходные!$B$8*E$16*(1-Исходные!$B$10)-Исходные!$B$4*Исходные!$B$5*(1+$A22)*(Исходные!$B$15/Исходные!$B$16/1000*Исходные!$B$17+Исходные!$B$21/1000*Исходные!$B$22) -> 13082440 | F22: =Исходные!$B$4*Исходные!$B$5*$A22*(Исходные!$B$6*Исходные!$B$7*Исходные!$B$8*F$16*(1-Исходные!$B$10)-Исходные!$B$11)+Исходные!$B$4*Исходные!$B$5*(1+$A22)*Исходные!$B$6*Исходные!$B$20*Исходные!$B$23*Исходные!$B$8*F$16*(1-Исходные!$B$10)-Исходные!$B$4*Исходные!$B$5*(1+$A22)*(Исходные!$B$15/Исходные!$B$16/1000*Исходные!$B$17+Исходные!$B$21/1000*Исходные!$B$22) -> 16166744
A23: 0.1 | B23: =Исходные!$B$4*Исходные!$B$5*$A23*(Исходные!$B$6*Исходные!$B$7*Исходные!$B$8*B$16*(1-Исходные!$B$10)-Исходные!$B$11)+Исходные!$B$4*Исходные!$B$5*(1+$A23)*Исходные!$B$6*Исходные!$B$20*Исходные!$B$23*Исходные!$B$8*B$16*(1-Исходные!$B$10)-Исходные!$B$4*Исходные!$B$5*(1+$A23)*(Исходные!$B$15/Исходные!$B$16/1000*Исходные!$B$17+Исходные!$B$21/1000*Исходные!$B$22) -> 7968860.2 | C23: =Исходные!$B$4*Исходные!$B$5*$A23*(Исходные!$B$6*Исходные!$B$7*Исходные!$B$8*C$16*(1-Исходные!$B$10)-Исходные!$B$11)+Исходные!$B$4*Исходные!$B$5*(1+$A23)*Исходные!$B$6*Исходные!$B$20*Исходные!$B$23*Исходные!$B$8*C$16*(1-Исходные!$B$10)-Исходные!$B$4*Исходные!$B$5*(1+$A23)*(Исходные!$B$15/Исходные!$B$16/1000*Исходные!$B$17+Исходные!$B$21/1000*Исходные!$B$22) -> 10892231 | D23: =Исходные!$B$4*Исходные!$B$5*$A23*(Исходные!$B$6*Исходные!$B$7*Исходные!$B$8*D$16*(1-Исходные!$B$10)-Исходные!$B$11)+Исходные!$B$4*Исходные!$B$5*(1+$A23)*Исходные!$B$6*Исходные!$B$20*Исходные!$B$23*Исходные!$B$8*D$16*(1-Исходные!$B$10)-Исходные!$B$4*Исходные!$B$5*(1+$A23)*(Исходные!$B$15/Исходные!$B$16/1000*Исходные!$B$17+Исходные!$B$21/1000*Исходные!$B$22) -> 15277288 | E23: =Исходные!$B$4*Исходные!$B$5*$A23*(Исходные!$B$6*Исходные!$B$7*Исходные!$B$8*E$16*(1-Исходные!$B$10)-Исходные!$B$11)+Исходные!$B$4*Исходные!$B$5*(1+$A23)*Исходные!$B$6*Исходные!$B$20*Исходные!$B$23*Исходные!$B$8*E$16*(1-Исходные!$B$10)-Исходные!$B$4*Исходные!$B$5*(1+$A23)*(Исходные!$B$15/Исходные!$B$16/1000*Исходные!$B$17+Исходные!$B$21/1000*Исходные!$B$22) -> 19662344 | F23: =Исходные!$B$4*Исходные!$B$5*$A23*(Исходные!$B$6*Исходные!$B$7*Исходные!$B$8*F$16*(1-Исходные!$B$10)-Исходные!$B$11)+Исходные!$B$4*Исходные!$B$5*(1+$A23)*Исходные!$B$6*Исходные!$B$20*Исходные!$B$23*Исходные!$B$8*F$16*(1-Исходные!$B$10)-Исходные!$B$4*Исходные!$B$5*(1+$A23)*(Исходные!$B$15/Исходные!$B$16/1000*Исходные!$B$17+Исходные!$B$21/1000*Исходные!$B$22) -> 24047401

Sheet Скоринг составов
A1: Сравнение составов-кандидатов при дозе 50 г/т по активу (ПРИМЕР — заменить результатами этапов 0–4)
A2: Барьеры (1/0): составы, не прошедшие хотя бы один барьер, получают 0 баллов. Веса критериев — в строке 3, редактируемые.
B3: Веса → | D3: 0.35 | E3: 0.35 | K3: 0.3
A4: Код | B4: Состав | C4: Снижение τy, % (этап 1) | D4: ΔCw, п.п. (этап 1) | E4: Сокращение t80, % (этап 2) | F4: Ca-стабильность (1/0, этап 0) | G4: Флотация (1/0, этап 3) | H4: Сгущение (1/0, этап 4) | I4: Цена продукта, $/кг | J4: Доля актива | K4: Стоимость, $/т руды | L4: Балл | M4: Место
A5: R1 | B5: Na-полиакрилат, Mw около 5 тыс. | C5: 28 | D5: 1.8 | E5: 4 | F5: 0 | G5: 1 | H5: 1 | I5: 1.6 | J5: 0.4 | K5: =50/J5/1000*I5 -> 0.2 | L5: =F5*G5*H5*($D$3*D5/MAX($D$5:$D$12)+$E$3*E5/MAX($E$5:$E$12)+$K$3*MIN($K$5:$K$12)/K5) -> 0 | M5: =IF(L5>0,RANK(L5,$L$5:$L$12),"—") -> —
A6: R2 | B6: АК/AMPS 90:10 | C6: 30 | D6: 2 | E6: 4.5 | F6: 1 | G6: 1 | H6: 1 | I6: 1.9 | J6: 0.4 | K6: =50/J6/1000*I6 -> 0.2375 | L6: =F6*G6*H6*($D$3*D6/MAX($D$5:$D$12)+$E$3*E6/MAX($E$5:$E$12)+$K$3*MIN($K$5:$K$12)/K6) -> 0.79513158 | M6: =IF(L6>0,RANK(L6,$L$5:$L$12),"—") -> 4
A7: R3 | B7: АК/AMPS 75:25 (компонент A) | C7: 33 | D7: 2.3 | E7: 5.5 | F7: 1 | G7: 1 | H7: 1 | I7: 2.2 | J7: 0.4 | K7: =50/J7/1000*I7 -> 0.275 | L7: =F7*G7*H7*($D$3*D7/MAX($D$5:$D$12)+$E$3*E7/MAX($E$5:$E$12)+$K$3*MIN($K$5:$K$12)/K7) -> 0.86101515 | M7: =IF(L7>0,RANK(L7,$L$5:$L$12),"—") -> 2
A8: R4 | B8: АК/AMPS 60:40 | C8: 29 | D8: 2 | E8: 5 | F8: 1 | G8: 1 | H8: 1 | I8: 2.6 | J8: 0.4 | K8: =50/J8/1000*I8 -> 0.325 | L8: =F8*G8*H8*($D$3*D8/MAX($D$5:$D$12)+$E$3*E8/MAX($E$5:$E$12)+$K$3*MIN($K$5:$K$12)/K8) -> 0.75628205 | M8: =IF(L8>0,RANK(L8,$L$5:$L$12),"—") -> 6
A9: R5 | B9: Терполимер АК/AMPS/т-БАА (компонент B) | C9: 35 | D9: 2.5 | E9: 5.8 | F9: 1 | G9: 1 | H9: 1 | I9: 3 | J9: 0.4 | K9: =50/J9/1000*I9 -> 0.375 | L9: =F9*G9*H9*($D$3*D9/MAX($D$5:$D$12)+$E$3*E9/MAX($E$5:$E$12)+$K$3*MIN($K$5:$K$12)/K9) -> 0.84833333 | M9: =IF(L9>0,RANK(L9,$L$5:$L$12),"—") -> 3
A10: R6 | B10: МВ-Cu-S (A:B = 30:8) | C10: 36 | D10: 2.5 | E10: 6 | F10: 1 | G10: 1 | H10: 1 | I10: 2.5 | J10: 0.38 | K10: =50/J10/1000*I10 -> 0.32894737 | L10: =F10*G10*H10*($D$3*D10/MAX($D$5:$D$12)+$E$3*E10/MAX($E$5:$E$12)+$K$3*MIN($K$5:$K$12)/K10) -> 0.8824 | M10: =IF(L10>0,RANK(L10,$L$5:$L$12),"—") -> 1
A11: R7 | B11: АК/AHPSE | C11: 31 | D11: 2.1 | E11: 5 | F11: 1 | G11: 1 | H11: 0 | I11: 2.8 | J11: 0.4 | K11: =50/J11/1000*I11 -> 0.35 | L11: =F11*G11*H11*($D$3*D11/MAX($D$5:$D$12)+$E$3*E11/MAX($E$5:$E$12)+$K$3*MIN($K$5:$K$12)/K11) -> 0 | M11: =IF(L11>0,RANK(L11,$L$5:$L$12),"—") -> —
A12: R8 | B12: Коммерческий эталон | C12: 34 | D12: 2.4 | E12: 5.7 | F12: 1 | G12: 1 | H12: 1 | I12: 4 | J12: 0.35 | K12: =50/J12/1000*I12 -> 0.57142857 | L12: =F12*G12*H12*($D$3*D12/MAX($D$5:$D$12)+$E$3*E12/MAX($E$5:$E$12)+$K$3*MIN($K$5:$K$12)/K12) -> 0.7735 | M12: =IF(L12>0,RANK(L12,$L$5:$L$12),"—") -> 5
A14: Балл = барьеры × (w1·ΔCw/max + w2·Δt80/max + w3·min(стоимость)/стоимость). Снижение τy — справочно. Цены и эффекты в примере — иллюстративные.
